nameko_opentelemetry/__init__.py
nameko_opentelemetry/amqp.py
nameko_opentelemetry/entrypoints.py
nameko_opentelemetry/events.py
nameko_opentelemetry/http.py
nameko_opentelemetry/messaging.py
nameko_opentelemetry/package.py
nameko_opentelemetry/rpc.py
nameko_opentelemetry/scrubbers.py
nameko_opentelemetry/timer.py
nameko_opentelemetry/utils.py
nameko_opentelemetry/version.py
opentelemetry_instrumentation_nameko-0.5.2.dist-info/LICENSE
opentelemetry_instrumentation_nameko-0.5.2.dist-info/METADATA
opentelemetry_instrumentation_nameko-0.5.2.dist-info/WHEEL
opentelemetry_instrumentation_nameko-0.5.2.dist-info/top_level.txt
opentelemetry_instrumentation_nameko-0.5.2.dist-info/zip-safe
opentelemetry_instrumentation_nameko-0.5.2.dist-info/RECORD
